{
 "1002256": {
  "Password": "iLoveDistSys",
  "Role": 100,
  "Username": "Sudipta"
 },
 "1003651": {
  "Password": "Reader",
  "Role": 3,
  "Username": "DevBahl"
 },
 "1003652": {
  "Password": "Reader",
  "Role": 2,
  "Username": "Jose"
 },
 "1003653": {
  "Password": "Reader",
  "Role": 4,
  "Username": "Aaron"
 },
 "1003654": {
  "Password": "Reader",
  "Role": 5,
  "Username": "JiaYi"
 },
 "1003655": {
  "Password": "Reader",
  "Role": 1,
  "Username": "Yuxuan"
 },
 "123456": {
  "Username": "FJdladjf",
  "Password": "afjlaksdjflkaj",
  "Role": 3
 }
}